{
  "_class": "shapeGroup",
  "do_objectID": "F5B7EC42-227B-4933-8874-A31E62B4BFD2",
  "exportOptions": {
    "_class": "exportOptions",
    "exportFormats": [],
    "includedLayerIds": [],
    "layerOptions": 0,
    "shouldTrim": false
  },
  "frame": {
    "_class": "rect",
    "constrainProportions": false,
    "height": 23.5,
    "width": 359,
    "x": 8,
    "y": 10
  },
  "isFlippedHorizontal": false,
  "isFlippedVertical": false,
  "isLocked": false,
  "isVisible": true,
  "layerListExpandedType": 0,
  "name": "Button Background",
  "nameIsFixed": true,
  "resizingType": 2,
  "rotation": 0,
  "shouldBreakMaskChain": false,
  "style": {
    "_class": "style",
    "borders": [
      {
        "_class": "border",
        "isEnabled": true,
        "color": {
          "_class": "color",
          "alpha": 1,
          "blue": 1,
          "green": 0.4627450980392158,
          "red": 0
        },
        "fillType": 0,
        "position": 1,
        "thickness": 1
      }
    ],
    "endDecorationType": 0,
    "miterLimit": 10,
    "sharedObjectID": "4DD785BE-6949-411C-BB8E-ABC249E1B7A9",
    "startDecorationType": 0
  },
  "hasClickThrough": false,
  "layers": [
    {
      "id": "597734BA-4BDA-4D25-AD8C-64099415FDA9",
      "class": "rectangle"
    }
  ],
  "clippingMaskMode": 0,
  "hasClippingMask": false,
  "windingRule": 1
}