{
  "_class": "group",
  "do_objectID": "5E2F4CCF-3AD4-483D-BA9D-2C9DDD8203CD",
  "exportOptions": {
    "_class": "exportOptions",
    "exportFormats": [],
    "includedLayerIds": [],
    "layerOptions": 0,
    "shouldTrim": false
  },
  "frame": {
    "_class": "rect",
    "constrainProportions": false,
    "height": 42,
    "width": 32,
    "x": 206,
    "y": 0
  },
  "isFlippedHorizontal": false,
  "isFlippedVertical": false,
  "isLocked": false,
  "isVisible": true,
  "layerListExpandedType": 0,
  "name": "B",
  "nameIsFixed": true,
  "resizingType": 0,
  "rotation": 0,
  "shouldBreakMaskChain": false,
  "style": {
    "_class": "style",
    "endDecorationType": 0,
    "miterLimit": 10,
    "startDecorationType": 0
  },
  "hasClickThrough": false,
  "layers": [
    {
      "id": "8E75A907-35E8-482A-87FA-83076C0C964D",
      "class": "shapeGroup"
    },
    {
      "id": "F5287726-1D23-4161-89A8-A71286A253BD",
      "class": "text"
    }
  ]
}