{
  "_class": "group",
  "do_objectID": "9DD4B29E-03F6-417C-ACCF-6F314AB8D38D",
  "exportOptions": {
    "_class": "exportOptions",
    "exportFormats": [],
    "includedLayerIds": [],
    "layerOptions": 0,
    "shouldTrim": false
  },
  "frame": {
    "_class": "rect",
    "constrainProportions": false,
    "height": 44,
    "width": 375,
    "x": 1,
    "y": 352
  },
  "isFlippedHorizontal": false,
  "isFlippedVertical": false,
  "isLocked": false,
  "isVisible": true,
  "layerListExpandedType": 0,
  "name": "Cell/Cell with Input",
  "nameIsFixed": false,
  "resizingType": 0,
  "rotation": 0,
  "shouldBreakMaskChain": false,
  "style": {
    "_class": "style",
    "endDecorationType": 0,
    "miterLimit": 10,
    "startDecorationType": 0
  },
  "hasClickThrough": false,
  "layers": [
    {
      "id": "13F99802-2447-48D7-A58E-264DA40565AC",
      "class": "shapeGroup"
    },
    {
      "id": "AD044B92-4052-4746-B50A-34DBBBD6CC71",
      "class": "shapeGroup"
    },
    {
      "id": "330B1527-E307-4908-90EE-DA41065C4055",
      "class": "text"
    },
    {
      "id": "A00CE5D0-12CE-421F-B0AF-909863AF82A2",
      "class": "text"
    }
  ]
}