{
  "_class": "shapeGroup",
  "clippingMaskMode": 0,
  "do_objectID": "4BED7AFA-696F-42BC-BA36-7A2527EC05DE",
  "exportOptions": {
    "_class": "exportOptions",
    "exportFormats": [
    ],
    "includedLayerIds": [
    ],
    "layerOptions": 0,
    "shouldTrim": false
  },
  "frame": {
    "_class": "rect",
    "constrainProportions": false,
    "height": 9.5,
    "width": 24.5,
    "x": 36,
    "y": 2.5
  },
  "hasClickThrough": false,
  "hasClippingMask": false,
  "isFlippedHorizontal": false,
  "isFlippedVertical": false,
  "isLocked": false,
  "isVisible": true,
  "layerListExpandedType": 1,
  "layers": [
    {
      "class": "rectangle",
      "id": "11CD3266-9C21-42B3-8FE9-D62F8FFC1C74"
    },
    {
      "class": "rectangle",
      "id": "02CE5946-905F-4E72-B6D3-600F1FBD4C76"
    },
    {
      "class": "rectangle",
      "id": "665C5EE5-D686-43E4-9FD3-54AA08C034A9"
    }
  ],
  "name": "Battery",
  "nameIsFixed": true,
  "originalObjectID": "AFB93CA4-6F52-4794-B820-BC43BA02A5AC",
  "resizingType": 0,
  "rotation": 0,
  "shouldBreakMaskChain": false,
  "style": {
    "_class": "style",
    "endDecorationType": 0,
    "fills": [
      {
        "_class": "fill",
        "color": {
          "_class": "color",
          "alpha": 1,
          "blue": 0.01176470588235294,
          "green": 0.01176470588235294,
          "red": 0.01176470588235294
        },
        "fillType": 0,
        "isEnabled": true,
        "noiseIndex": 0,
        "noiseIntensity": 0,
        "patternFillType": 0,
        "patternTileScale": 1
      }
    ],
    "miterLimit": 10,
    "startDecorationType": 0
  },
  "windingRule": 1
}