{
  "_class": "group",
  "do_objectID": "DEA39D7F-32C1-4151-988D-6475A0BD7EA0",
  "exportOptions": {
    "_class": "exportOptions",
    "exportFormats": [],
    "includedLayerIds": [],
    "layerOptions": 0,
    "shouldTrim": false
  },
  "frame": {
    "_class": "rect",
    "constrainProportions": false,
    "height": 44,
    "width": 375,
    "x": 0,
    "y": 0
  },
  "isFlippedHorizontal": false,
  "isFlippedVertical": false,
  "isLocked": false,
  "isVisible": true,
  "layerListExpandedType": 0,
  "name": "Cell/Cell",
  "nameIsFixed": false,
  "resizingType": 0,
  "rotation": 0,
  "shouldBreakMaskChain": false,
  "style": {
    "_class": "style",
    "endDecorationType": 0,
    "miterLimit": 10,
    "startDecorationType": 0
  },
  "hasClickThrough": false,
  "layers": [
    {
      "id": "8DFC4498-98C9-489C-B501-338A1C75D794",
      "class": "shapeGroup"
    },
    {
      "id": "4D5C9526-0217-41BC-9FC2-59809CE6DF90",
      "class": "text"
    },
    {
      "id": "F8C426A2-8B93-49E0-B533-161555F987FD",
      "class": "shapeGroup"
    },
    {
      "id": "B2BD95E9-F9A6-4400-95A4-C40BCEC2FD13",
      "class": "text"
    },
    {
      "id": "705137EA-CD0B-4241-A316-FA6F215E0ADF",
      "class": "shapeGroup"
    }
  ]
}