{
  "_class": "group",
  "do_objectID": "C38C0F07-86E8-4399-975A-63CE0E732468",
  "exportOptions": {
    "_class": "exportOptions",
    "exportFormats": [
    ],
    "includedLayerIds": [
    ],
    "layerOptions": 0,
    "shouldTrim": false
  },
  "frame": {
    "_class": "rect",
    "constrainProportions": false,
    "height": 42,
    "width": 32,
    "x": 300,
    "y": 0
  },
  "hasClickThrough": false,
  "isFlippedHorizontal": false,
  "isFlippedVertical": false,
  "isLocked": false,
  "isVisible": true,
  "layerListExpandedType": 0,
  "layers": [
    {
      "class": "shapeGroup",
      "id": "73EC2126-F622-41A8-BC07-200BF36BD57C"
    },
    {
      "class": "text",
      "id": "4B40FEE8-ABB0-4ED1-887E-0CB3C0DB9601"
    }
  ],
  "name": "o",
  "nameIsFixed": true,
  "resizingType": 0,
  "rotation": 0,
  "shouldBreakMaskChain": false,
  "style": {
    "_class": "style",
    "endDecorationType": 0,
    "miterLimit": 10,
    "startDecorationType": 0
  }
}